aigency/__init__.py
aigency/aigency.py
aigency/agents/client.py
aigency/agents/communicator.py
aigency/agents/executor.py
aigency/agents/generator.py
aigency/observability/observability.py
aigency/observability/phoenix.py
aigency/schemas/aigency_config.py
aigency/schemas/agent/agent.py
aigency/schemas/agent/model.py
aigency/schemas/agent/remote_agent.py
aigency/schemas/agent/skills.py
aigency/schemas/agent/tools.py
aigency/schemas/metadata/metadata.py
aigency/schemas/observability/observability.py
aigency/schemas/observability/phoenix.py
aigency/schemas/service/capabilities.py
aigency/schemas/service/interface.py
aigency/schemas/service/service.py
aigency/tools/generator.py
aigency/utils/config_service.py
aigency/utils/logger.py
aigency/utils/singleton.py
aigency/utils/utils.py
aigency-0.1.1.dist-info/licenses/LICENSE.txt
aigency-0.1.1.dist-info/METADATA
aigency-0.1.1.dist-info/WHEEL
aigency-0.1.1.dist-info/top_level.txt
aigency-0.1.1.dist-info/RECORD
