Metadata-Version: 2.4
Name: aigency
Version: 0.1.1
Summary: AI Agent Development Acceleration Kit — build, run, and orchestrate intelligent agents with a production‑ready Agent‑to‑Agent (A2A) runtime.
Keywords: ai,agents,a2a,llm,automation
Classifier: Development Status :: 4 - Beta
Classifier: Intended Audience :: Developers
Classifier: Programming Language :: Python :: 3
Classifier: Programming Language :: Python :: 3.12
Requires-Python: >=3.12
License-File: LICENSE.txt
Requires-Dist: google-adk>=1.11.0
Requires-Dist: a2a-sdk>=0.3.0
Requires-Dist: litellm<1.73.0,>=1.72.6
Requires-Dist: pyyaml==6.0.2
Requires-Dist: PyJWT==2.10.1
Requires-Dist: openinference-instrumentation-google-adk>=0.1.3
Requires-Dist: arize-phoenix-otel>=0.12.1
Dynamic: license-file
